[
  {
    "sku_config": "11136ACAEAAP",
    "fk_customer": "4487542",
    "order_date_key": "11-04-2023",
    "order_nr": "AE1142438499",
    "wishlist_customer": "17125619",
    "wishlist_sku": "11136ACAEAAP",
    "wishlist_updated_at": "2023-04-08 03:21:18 UTC",
    "brand": "Seventy Five",
    "name": "Smart Watch W/ Dynamic Heart Rate & Multi Features",
    "activated_at": "2021-07-11 10:56:14 UTC",
    "season": "co",
    "color": "Blue",
    "department": "accessories",
    "category": "Watches",
    "subcategory": "Smart Watches",
    "product_gender": "Male",
    "age_group": "Adult",
    "price": "199",
    "price_level": "pl5",
    "merch_type": "Private",
    "occasion": "Casual",
    "short_description": "<ul><li>Processor - GR5515</li><li>Display: 1.69\" Color Screen/240*280</li><li>Battery Capacity: 190 mAh Lithium-ion battery</li><li>Built-in: Heart Rate Monitor</li><li>Waterproof: IP67</li><li>App name: Dafit</li><li>Working Time: 5 - 7 days</li><li>Reminder for incoming Call & SMS</li><li>Alarm/Anti-lost/Sedentary reminder</li><li>Time; date and week display/Power display/Find equipment</li><li>Pedometer/Sleeping monitor/Remote camera control/Music control</li><li>Message push: Skype; whatsapp; wechat; facebook; twitter etc.</li><li>Multiple sport modes/wake up screen by turn wrist</li><li>OS: Android 5.1 and above & IOS 10.0 and above</li><li>Charge the watch before first use</li></ul>",
    "namshi_description": "Smart Watch W/ Dynamic Heart Rate & Multi Features",
    "special_type": "Discounted",
    "world_tag": "Young Fashion",
    "customer_gender": "",
    "customer_generation": "1981-1996 Milennials",
    "customer_country_name": "United Arab Emirates",
    "RPC_gross_per_month": "239.5472131",
    "RPC_net_per_month": "230.5308197",
    "TPC_per_month": "1.459016393",
    "wishlist_customer_gender": "female",
    "wishlist_customer_generation": "Not Available",
    "wishlist_customer_country": "Saudi Arabia",
    "wishlist_rpc_gross": "",
    "wishlist_rpc_net": "",
    "wishlist_tpc": ""
  },
  {
    "sku_config": "11136ACDSAHP",
    "fk_customer": "4487542",
    "order_date_key": "11-04-2023",
    "order_nr": "AE1142438499",
    "wishlist_customer": "915127",
    "wishlist_sku": "11136ACDSAHP",
    "wishlist_updated_at": "2023-04-10 00:37:03 UTC",
    "brand": "Seventy Five",
    "name": "Smart Watch With Health And Fitness Features",
    "activated_at": "2021-09-08 07:21:13 UTC",
    "season": "co",
    "color": "Black",
    "department": "accessories",
    "category": "Watches",
    "subcategory": "Smart Watches",
    "product_gender": "Male",
    "age_group": "Adult",
    "price": "199",
    "price_level": "pl5",
    "merch_type": "Private",
    "occasion": "Casual",
    "short_description": "<ul><li>Durable and lightweight gel silicon wrist straps</li><li>Smart watch with display 1.3 inch</li><li>HD Colour Screen 240 x 240 Resolution</li><li>Battery Capacity: 200mAH</li><li>Water proof level: IP67 equivalent to 1 m</li></ul>",
    "namshi_description": "Smart Watch With Health And Fitness Features",
    "special_type": "Discounted",
    "world_tag": "Young Fashion",
    "customer_gender": "",
    "customer_generation": "1981-1996 Milennials",
    "customer_country_name": "United Arab Emirates",
    "RPC_gross_per_month": "239.5472131",
    "RPC_net_per_month": "230.5308197",
    "TPC_per_month": "1.459016393",
    "wishlist_customer_gender": "female",
    "wishlist_customer_generation": "1981-1996 Milennials",
    "wishlist_customer_country": "Saudi Arabia",
    "wishlist_rpc_gross": "143.9875532",
    "wishlist_rpc_net": "78.54542553",
    "wishlist_tpc": "0.308510638"
  },
  {
    "sku_config": "11136ACAEAAP",
    "fk_customer": "4487542",
    "order_date_key": "11-04-2023",
    "order_nr": "AE1142438499",
    "wishlist_customer": "9375723",
    "wishlist_sku": "11136ACAEAAP",
    "wishlist_updated_at": "2023-04-08 10:50:40 UTC",
    "brand": "Seventy Five",
    "name": "Smart Watch W/ Dynamic Heart Rate & Multi Features",
    "activated_at": "2021-07-11 10:56:14 UTC",
    "season": "co",
    "color": "Blue",
    "department": "accessories",
    "category": "Watches",
    "subcategory": "Smart Watches",
    "product_gender": "Male",
    "age_group": "Adult",
    "price": "199",
    "price_level": "pl5",
    "merch_type": "Private",
    "occasion": "Casual",
    "short_description": "<ul><li>Processor - GR5515</li><li>Display: 1.69\" Color Screen/240*280</li><li>Battery Capacity: 190 mAh Lithium-ion battery</li><li>Built-in: Heart Rate Monitor</li><li>Waterproof: IP67</li><li>App name: Dafit</li><li>Working Time: 5 - 7 days</li><li>Reminder for incoming Call & SMS</li><li>Alarm/Anti-lost/Sedentary reminder</li><li>Time; date and week display/Power display/Find equipment</li><li>Pedometer/Sleeping monitor/Remote camera control/Music control</li><li>Message push: Skype; whatsapp; wechat; facebook; twitter etc.</li><li>Multiple sport modes/wake up screen by turn wrist</li><li>OS: Android 5.1 and above & IOS 10.0 and above</li><li>Charge the watch before first use</li></ul>",
    "namshi_description": "Smart Watch W/ Dynamic Heart Rate & Multi Features",
    "special_type": "Discounted",
    "world_tag": "Young Fashion",
    "customer_gender": "",
    "customer_generation": "1981-1996 Milennials",
    "customer_country_name": "United Arab Emirates",
    "RPC_gross_per_month": "239.5472131",
    "RPC_net_per_month": "230.5308197",
    "TPC_per_month": "1.459016393",
    "wishlist_customer_gender": "",
    "wishlist_customer_generation": "1965-1980 Generation X",
    "wishlist_customer_country": "Saudi Arabia",
    "wishlist_rpc_gross": "43.77",
    "wishlist_rpc_net": "39.2736",
    "wishlist_tpc": "0.16"
  },
  {
    "sku_config": "11136ACDSAHP",
    "fk_customer": "4487542",
    "order_date_key": "11-04-2023",
    "order_nr": "AE1142438499",
    "wishlist_customer": "12440589",
    "wishlist_sku": "11136ACDSAHP",
    "wishlist_updated_at": "2023-04-05 16:36:36 UTC",
    "brand": "Seventy Five",
    "name": "Smart Watch With Health And Fitness Features",
    "activated_at": "2021-09-08 07:21:13 UTC",
    "season": "co",
    "color": "Black",
    "department": "accessories",
    "category": "Watches",
    "subcategory": "Smart Watches",
    "product_gender": "Male",
    "age_group": "Adult",
    "price": "199",
    "price_level": "pl5",
    "merch_type": "Private",
    "occasion": "Casual",
    "short_description": "<ul><li>Durable and lightweight gel silicon wrist straps</li><li>Smart watch with display 1.3 inch</li><li>HD Colour Screen 240 x 240 Resolution</li><li>Battery Capacity: 200mAH</li><li>Water proof level: IP67 equivalent to 1 m</li></ul>",
    "namshi_description": "Smart Watch With Health And Fitness Features",
    "special_type": "Discounted",
    "world_tag": "Young Fashion",
    "customer_gender": "",
    "customer_generation": "1981-1996 Milennials",
    "customer_country_name": "United Arab Emirates",
    "RPC_gross_per_month": "239.5472131",
    "RPC_net_per_month": "230.5308197",
    "TPC_per_month": "1.459016393",
    "wishlist_customer_gender": "female",
    "wishlist_customer_generation": "1981-1996 Milennials",
    "wishlist_customer_country": "Saudi Arabia",
    "wishlist_rpc_gross": "",
    "wishlist_rpc_net": "",
    "wishlist_tpc": ""
  },
  {
    "sku_config": "11136ACAEAAP",
    "fk_customer": "4487542",
    "order_date_key": "11-04-2023",
    "order_nr": "AE1142438499",
    "wishlist_customer": "16836054",
    "wishlist_sku": "11136ACAEAAP",
    "wishlist_updated_at": "2023-04-01 10:59:13 UTC",
    "brand": "Seventy Five",
    "name": "Smart Watch W/ Dynamic Heart Rate & Multi Features",
    "activated_at": "2021-07-11 10:56:14 UTC",
    "season": "co",
    "color": "Blue",
    "department": "accessories",
    "category": "Watches",
    "subcategory": "Smart Watches",
    "product_gender": "Male",
    "age_group": "Adult",
    "price": "199",
    "price_level": "pl5",
    "merch_type": "Private",
    "occasion": "Casual",
    "short_description": "<ul><li>Processor - GR5515</li><li>Display: 1.69\" Color Screen/240*280</li><li>Battery Capacity: 190 mAh Lithium-ion battery</li><li>Built-in: Heart Rate Monitor</li><li>Waterproof: IP67</li><li>App name: Dafit</li><li>Working Time: 5 - 7 days</li><li>Reminder for incoming Call & SMS</li><li>Alarm/Anti-lost/Sedentary reminder</li><li>Time; date and week display/Power display/Find equipment</li><li>Pedometer/Sleeping monitor/Remote camera control/Music control</li><li>Message push: Skype; whatsapp; wechat; facebook; twitter etc.</li><li>Multiple sport modes/wake up screen by turn wrist</li><li>OS: Android 5.1 and above & IOS 10.0 and above</li><li>Charge the watch before first use</li></ul>",
    "namshi_description": "Smart Watch W/ Dynamic Heart Rate & Multi Features",
    "special_type": "Discounted",
    "world_tag": "Young Fashion",
    "customer_gender": "",
    "customer_generation": "1981-1996 Milennials",
    "customer_country_name": "United Arab Emirates",
    "RPC_gross_per_month": "239.5472131",
    "RPC_net_per_month": "230.5308197",
    "TPC_per_month": "1.459016393",
    "wishlist_customer_gender": "male",
    "wishlist_customer_generation": "Not Available",
    "wishlist_customer_country": "Saudi Arabia",
    "wishlist_rpc_gross": "232.47",
    "wishlist_rpc_net": "232.47",
    "wishlist_tpc": "1"
  },
  {
    "sku_config": "11136ACDSAHP",
    "fk_customer": "4487542",
    "order_date_key": "11-04-2023",
    "order_nr": "AE1142438499",
    "wishlist_customer": "5562334",
    "wishlist_sku": "11136ACDSAHP",
    "wishlist_updated_at": "2023-04-03 02:21:32 UTC",
    "brand": "Seventy Five",
    "name": "Smart Watch With Health And Fitness Features",
    "activated_at": "2021-09-08 07:21:13 UTC",
    "season": "co",
    "color": "Black",
    "department": "accessories",
    "category": "Watches",
    "subcategory": "Smart Watches",
    "product_gender": "Male",
    "age_group": "Adult",
    "price": "199",
    "price_level": "pl5",
    "merch_type": "Private",
    "occasion": "Casual",
    "short_description": "<ul><li>Durable and lightweight gel silicon wrist straps</li><li>Smart watch with display 1.3 inch</li><li>HD Colour Screen 240 x 240 Resolution</li><li>Battery Capacity: 200mAH</li><li>Water proof level: IP67 equivalent to 1 m</li></ul>",
    "namshi_description": "Smart Watch With Health And Fitness Features",
    "special_type": "Discounted",
    "world_tag": "Young Fashion",
    "customer_gender": "",
    "customer_generation": "1981-1996 Milennials",
    "customer_country_name": "United Arab Emirates",
    "RPC_gross_per_month": "239.5472131",
    "RPC_net_per_month": "230.5308197",
    "TPC_per_month": "1.459016393",
    "wishlist_customer_gender": "",
    "wishlist_customer_generation": "1997-2012 Generation Z",
    "wishlist_customer_country": "Saudi Arabia",
    "wishlist_rpc_gross": "77.74156863",
    "wishlist_rpc_net": "41.44294118",
    "wishlist_tpc": "0.254901961"
  },
  {
    "sku_config": "11136ACAEAAP",
    "fk_customer": "4487542",
    "order_date_key": "11-04-2023",
    "order_nr": "AE1142438499",
    "wishlist_customer": "12801616",
    "wishlist_sku": "11136ACAEAAP",
    "wishlist_updated_at": "2023-04-04 18:00:11 UTC",
    "brand": "Seventy Five",
    "name": "Smart Watch W/ Dynamic Heart Rate & Multi Features",
    "activated_at": "2021-07-11 10:56:14 UTC",
    "season": "co",
    "color": "Blue",
    "department": "accessories",
    "category": "Watches",
    "subcategory": "Smart Watches",
    "product_gender": "Male",
    "age_group": "Adult",
    "price": "199",
    "price_level": "pl5",
    "merch_type": "Private",
    "occasion": "Casual",
    "short_description": "<ul><li>Processor - GR5515</li><li>Display: 1.69\" Color Screen/240*280</li><li>Battery Capacity: 190 mAh Lithium-ion battery</li><li>Built-in: Heart Rate Monitor</li><li>Waterproof: IP67</li><li>App name: Dafit</li><li>Working Time: 5 - 7 days</li><li>Reminder for incoming Call & SMS</li><li>Alarm/Anti-lost/Sedentary reminder</li><li>Time; date and week display/Power display/Find equipment</li><li>Pedometer/Sleeping monitor/Remote camera control/Music control</li><li>Message push: Skype; whatsapp; wechat; facebook; twitter etc.</li><li>Multiple sport modes/wake up screen by turn wrist</li><li>OS: Android 5.1 and above & IOS 10.0 and above</li><li>Charge the watch before first use</li></ul>",
    "namshi_description": "Smart Watch W/ Dynamic Heart Rate & Multi Features",
    "special_type": "Discounted",
    "world_tag": "Young Fashion",
    "customer_gender": "",
    "customer_generation": "1981-1996 Milennials",
    "customer_country_name": "United Arab Emirates",
    "RPC_gross_per_month": "239.5472131",
    "RPC_net_per_month": "230.5308197",
    "TPC_per_month": "1.459016393",
    "wishlist_customer_gender": "female",
    "wishlist_customer_generation": "1981-1996 Milennials",
    "wishlist_customer_country": "Kuwait",
    "wishlist_rpc_gross": "",
    "wishlist_rpc_net": "",
    "wishlist_tpc": ""
  },
  {
    "sku_config": "11136ACAEAAP",
    "fk_customer": "4487542",
    "order_date_key": "11-04-2023",
    "order_nr": "AE1142438499",
    "wishlist_customer": "14530794",
    "wishlist_sku": "11136ACAEAAP",
    "wishlist_updated_at": "2023-04-05 19:36:47 UTC",
    "brand": "Seventy Five",
    "name": "Smart Watch W/ Dynamic Heart Rate & Multi Features",
    "activated_at": "2021-07-11 10:56:14 UTC",
    "season": "co",
    "color": "Blue",
    "department": "accessories",
    "category": "Watches",
    "subcategory": "Smart Watches",
    "product_gender": "Male",
    "age_group": "Adult",
    "price": "199",
    "price_level": "pl5",
    "merch_type": "Private",
    "occasion": "Casual",
    "short_description": "<ul><li>Processor - GR5515</li><li>Display: 1.69\" Color Screen/240*280</li><li>Battery Capacity: 190 mAh Lithium-ion battery</li><li>Built-in: Heart Rate Monitor</li><li>Waterproof: IP67</li><li>App name: Dafit</li><li>Working Time: 5 - 7 days</li><li>Reminder for incoming Call & SMS</li><li>Alarm/Anti-lost/Sedentary reminder</li><li>Time; date and week display/Power display/Find equipment</li><li>Pedometer/Sleeping monitor/Remote camera control/Music control</li><li>Message push: Skype; whatsapp; wechat; facebook; twitter etc.</li><li>Multiple sport modes/wake up screen by turn wrist</li><li>OS: Android 5.1 and above & IOS 10.0 and above</li><li>Charge the watch before first use</li></ul>",
    "namshi_description": "Smart Watch W/ Dynamic Heart Rate & Multi Features",
    "special_type": "Discounted",
    "world_tag": "Young Fashion",
    "customer_gender": "",
    "customer_generation": "1981-1996 Milennials",
    "customer_country_name": "United Arab Emirates",
    "RPC_gross_per_month": "239.5472131",
    "RPC_net_per_month": "230.5308197",
    "TPC_per_month": "1.459016393",
    "wishlist_customer_gender": "female",
    "wishlist_customer_generation": "1997-2012 Generation Z",
    "wishlist_customer_country": "Saudi Arabia",
    "wishlist_rpc_gross": "145.5316667",
    "wishlist_rpc_net": "73.70833333",
    "wishlist_tpc": "0.833333333"
  },
  {
    "sku_config": "11136ACAEAAP",
    "fk_customer": "4487542",
    "order_date_key": "11-04-2023",
    "order_nr": "AE1142438499",
    "wishlist_customer": "809126",
    "wishlist_sku": "11136ACAEAAP",
    "wishlist_updated_at": "2023-04-05 01:51:04 UTC",
    "brand": "Seventy Five",
    "name": "Smart Watch W/ Dynamic Heart Rate & Multi Features",
    "activated_at": "2021-07-11 10:56:14 UTC",
    "season": "co",
    "color": "Blue",
    "department": "accessories",
    "category": "Watches",
    "subcategory": "Smart Watches",
    "product_gender": "Male",
    "age_group": "Adult",
    "price": "199",
    "price_level": "pl5",
    "merch_type": "Private",
    "occasion": "Casual",
    "short_description": "<ul><li>Processor - GR5515</li><li>Display: 1.69\" Color Screen/240*280</li><li>Battery Capacity: 190 mAh Lithium-ion battery</li><li>Built-in: Heart Rate Monitor</li><li>Waterproof: IP67</li><li>App name: Dafit</li><li>Working Time: 5 - 7 days</li><li>Reminder for incoming Call & SMS</li><li>Alarm/Anti-lost/Sedentary reminder</li><li>Time; date and week display/Power display/Find equipment</li><li>Pedometer/Sleeping monitor/Remote camera control/Music control</li><li>Message push: Skype; whatsapp; wechat; facebook; twitter etc.</li><li>Multiple sport modes/wake up screen by turn wrist</li><li>OS: Android 5.1 and above & IOS 10.0 and above</li><li>Charge the watch before first use</li></ul>",
    "namshi_description": "Smart Watch W/ Dynamic Heart Rate & Multi Features",
    "special_type": "Discounted",
    "world_tag": "Young Fashion",
    "customer_gender": "",
    "customer_generation": "1981-1996 Milennials",
    "customer_country_name": "United Arab Emirates",
    "RPC_gross_per_month": "239.5472131",
    "RPC_net_per_month": "230.5308197",
    "TPC_per_month": "1.459016393",
    "wishlist_customer_gender": "female",
    "wishlist_customer_generation": "1981-1996 Milennials",
    "wishlist_customer_country": "Saudi Arabia",
    "wishlist_rpc_gross": "113.6991667",
    "wishlist_rpc_net": "88.1490625",
    "wishlist_tpc": "0.333333333"
  },
  {
    "sku_config": "11136ACDSAHP",
    "fk_customer": "4487542",
    "order_date_key": "11-04-2023",
    "order_nr": "AE1142438499",
    "wishlist_customer": "10533587",
    "wishlist_sku": "11136ACDSAHP",
    "wishlist_updated_at": "2023-04-08 22:10:50 UTC",
    "brand": "Seventy Five",
    "name": "Smart Watch With Health And Fitness Features",
    "activated_at": "2021-09-08 07:21:13 UTC",
    "season": "co",
    "color": "Black",
    "department": "accessories",
    "category": "Watches",
    "subcategory": "Smart Watches",
    "product_gender": "Male",
    "age_group": "Adult",
    "price": "199",
    "price_level": "pl5",
    "merch_type": "Private",
    "occasion": "Casual",
    "short_description": "<ul><li>Durable and lightweight gel silicon wrist straps</li><li>Smart watch with display 1.3 inch</li><li>HD Colour Screen 240 x 240 Resolution</li><li>Battery Capacity: 200mAH</li><li>Water proof level: IP67 equivalent to 1 m</li></ul>",
    "namshi_description": "Smart Watch With Health And Fitness Features",
    "special_type": "Discounted",
    "world_tag": "Young Fashion",
    "customer_gender": "",
    "customer_generation": "1981-1996 Milennials",
    "customer_country_name": "United Arab Emirates",
    "RPC_gross_per_month": "239.5472131",
    "RPC_net_per_month": "230.5308197",
    "TPC_per_month": "1.459016393",
    "wishlist_customer_gender": "female",
    "wishlist_customer_generation": "Not Available",
    "wishlist_customer_country": "Saudi Arabia",
    "wishlist_rpc_gross": "366.6533333",
    "wishlist_rpc_net": "321.7466667",
    "wishlist_tpc": "0.583333333"
  },
  {
    "sku_config": "11136ACAEAAP",
    "fk_customer": "4487542",
    "order_date_key": "11-04-2023",
    "order_nr": "AE1142438499",
    "wishlist_customer": "8248322",
    "wishlist_sku": "11136ACAEAAP",
    "wishlist_updated_at": "2023-04-06 10:22:04 UTC",
    "brand": "Seventy Five",
    "name": "Smart Watch W/ Dynamic Heart Rate & Multi Features",
    "activated_at": "2021-07-11 10:56:14 UTC",
    "season": "co",
    "color": "Blue",
    "department": "accessories",
    "category": "Watches",
    "subcategory": "Smart Watches",
    "product_gender": "Male",
    "age_group": "Adult",
    "price": "199",
    "price_level": "pl5",
    "merch_type": "Private",
    "occasion": "Casual",
    "short_description": "<ul><li>Processor - GR5515</li><li>Display: 1.69\" Color Screen/240*280</li><li>Battery Capacity: 190 mAh Lithium-ion battery</li><li>Built-in: Heart Rate Monitor</li><li>Waterproof: IP67</li><li>App name: Dafit</li><li>Working Time: 5 - 7 days</li><li>Reminder for incoming Call & SMS</li><li>Alarm/Anti-lost/Sedentary reminder</li><li>Time; date and week display/Power display/Find equipment</li><li>Pedometer/Sleeping monitor/Remote camera control/Music control</li><li>Message push: Skype; whatsapp; wechat; facebook; twitter etc.</li><li>Multiple sport modes/wake up screen by turn wrist</li><li>OS: Android 5.1 and above & IOS 10.0 and above</li><li>Charge the watch before first use</li></ul>",
    "namshi_description": "Smart Watch W/ Dynamic Heart Rate & Multi Features",
    "special_type": "Discounted",
    "world_tag": "Young Fashion",
    "customer_gender": "",
    "customer_generation": "1981-1996 Milennials",
    "customer_country_name": "United Arab Emirates",
    "RPC_gross_per_month": "239.5472131",
    "RPC_net_per_month": "230.5308197",
    "TPC_per_month": "1.459016393",
    "wishlist_customer_gender": "female",
    "wishlist_customer_generation": "Not Available",
    "wishlist_customer_country": "Saudi Arabia",
    "wishlist_rpc_gross": "268.8188235",
    "wishlist_rpc_net": "156.9311765",
    "wishlist_tpc": "0.558823529"
  },
  {
    "sku_config": "11136ACAEAAP",
    "fk_customer": "4487542",
    "order_date_key": "11-04-2023",
    "order_nr": "AE1142438499",
    "wishlist_customer": "7442233",
    "wishlist_sku": "11136ACAEAAP",
    "wishlist_updated_at": "2023-04-08 01:42:50 UTC",
    "brand": "Seventy Five",
    "name": "Smart Watch W/ Dynamic Heart Rate & Multi Features",
    "activated_at": "2021-07-11 10:56:14 UTC",
    "season": "co",
    "color": "Blue",
    "department": "accessories",
    "category": "Watches",
    "subcategory": "Smart Watches",
    "product_gender": "Male",
    "age_group": "Adult",
    "price": "199",
    "price_level": "pl5",
    "merch_type": "Private",
    "occasion": "Casual",
    "short_description": "<ul><li>Processor - GR5515</li><li>Display: 1.69\" Color Screen/240*280</li><li>Battery Capacity: 190 mAh Lithium-ion battery</li><li>Built-in: Heart Rate Monitor</li><li>Waterproof: IP67</li><li>App name: Dafit</li><li>Working Time: 5 - 7 days</li><li>Reminder for incoming Call & SMS</li><li>Alarm/Anti-lost/Sedentary reminder</li><li>Time; date and week display/Power display/Find equipment</li><li>Pedometer/Sleeping monitor/Remote camera control/Music control</li><li>Message push: Skype; whatsapp; wechat; facebook; twitter etc.</li><li>Multiple sport modes/wake up screen by turn wrist</li><li>OS: Android 5.1 and above & IOS 10.0 and above</li><li>Charge the watch before first use</li></ul>",
    "namshi_description": "Smart Watch W/ Dynamic Heart Rate & Multi Features",
    "special_type": "Discounted",
    "world_tag": "Young Fashion",
    "customer_gender": "",
    "customer_generation": "1981-1996 Milennials",
    "customer_country_name": "United Arab Emirates",
    "RPC_gross_per_month": "239.5472131",
    "RPC_net_per_month": "230.5308197",
    "TPC_per_month": "1.459016393",
    "wishlist_customer_gender": "female",
    "wishlist_customer_generation": "Not Available",
    "wishlist_customer_country": "Saudi Arabia",
    "wishlist_rpc_gross": "11.29931034",
    "wishlist_rpc_net": "0",
    "wishlist_tpc": "0.068965517"
  },
  {
    "sku_config": "11136ACDSAHP",
    "fk_customer": "4487542",
    "order_date_key": "11-04-2023",
    "order_nr": "AE1142438499",
    "wishlist_customer": "1486494",
    "wishlist_sku": "11136ACDSAHP",
    "wishlist_updated_at": "2023-04-04 06:51:14 UTC",
    "brand": "Seventy Five",
    "name": "Smart Watch With Health And Fitness Features",
    "activated_at": "2021-09-08 07:21:13 UTC",
    "season": "co",
    "color": "Black",
    "department": "accessories",
    "category": "Watches",
    "subcategory": "Smart Watches",
    "product_gender": "Male",
    "age_group": "Adult",
    "price": "199",
    "price_level": "pl5",
    "merch_type": "Private",
    "occasion": "Casual",
    "short_description": "<ul><li>Durable and lightweight gel silicon wrist straps</li><li>Smart watch with display 1.3 inch</li><li>HD Colour Screen 240 x 240 Resolution</li><li>Battery Capacity: 200mAH</li><li>Water proof level: IP67 equivalent to 1 m</li></ul>",
    "namshi_description": "Smart Watch With Health And Fitness Features",
    "special_type": "Discounted",
    "world_tag": "Young Fashion",
    "customer_gender": "",
    "customer_generation": "1981-1996 Milennials",
    "customer_country_name": "United Arab Emirates",
    "RPC_gross_per_month": "239.5472131",
    "RPC_net_per_month": "230.5308197",
    "TPC_per_month": "1.459016393",
    "wishlist_customer_gender": "female",
    "wishlist_customer_generation": "1981-1996 Milennials",
    "wishlist_customer_country": "Bahrain",
    "wishlist_rpc_gross": "51.48816092",
    "wishlist_rpc_net": "39.81551724",
    "wishlist_tpc": "0.149425287"
  },
  {
    "sku_config": "11136ACAEAAP",
    "fk_customer": "4487542",
    "order_date_key": "11-04-2023",
    "order_nr": "AE1142438499",
    "wishlist_customer": "12656802",
    "wishlist_sku": "11136ACAEAAP",
    "wishlist_updated_at": "2023-04-05 12:33:58 UTC",
    "brand": "Seventy Five",
    "name": "Smart Watch W/ Dynamic Heart Rate & Multi Features",
    "activated_at": "2021-07-11 10:56:14 UTC",
    "season": "co",
    "color": "Blue",
    "department": "accessories",
    "category": "Watches",
    "subcategory": "Smart Watches",
    "product_gender": "Male",
    "age_group": "Adult",
    "price": "199",
    "price_level": "pl5",
    "merch_type": "Private",
    "occasion": "Casual",
    "short_description": "<ul><li>Processor - GR5515</li><li>Display: 1.69\" Color Screen/240*280</li><li>Battery Capacity: 190 mAh Lithium-ion battery</li><li>Built-in: Heart Rate Monitor</li><li>Waterproof: IP67</li><li>App name: Dafit</li><li>Working Time: 5 - 7 days</li><li>Reminder for incoming Call & SMS</li><li>Alarm/Anti-lost/Sedentary reminder</li><li>Time; date and week display/Power display/Find equipment</li><li>Pedometer/Sleeping monitor/Remote camera control/Music control</li><li>Message push: Skype; whatsapp; wechat; facebook; twitter etc.</li><li>Multiple sport modes/wake up screen by turn wrist</li><li>OS: Android 5.1 and above & IOS 10.0 and above</li><li>Charge the watch before first use</li></ul>",
    "namshi_description": "Smart Watch W/ Dynamic Heart Rate & Multi Features",
    "special_type": "Discounted",
    "world_tag": "Young Fashion",
    "customer_gender": "",
    "customer_generation": "1981-1996 Milennials",
    "customer_country_name": "United Arab Emirates",
    "RPC_gross_per_month": "239.5472131",
    "RPC_net_per_month": "230.5308197",
    "TPC_per_month": "1.459016393",
    "wishlist_customer_gender": "female",
    "wishlist_customer_generation": "Not Available",
    "wishlist_customer_country": "Saudi Arabia",
    "wishlist_rpc_gross": "113.9347059",
    "wishlist_rpc_net": "82.07647059",
    "wishlist_tpc": "0.352941176"
  },
  {
    "sku_config": "11136ACAEAAP",
    "fk_customer": "4487542",
    "order_date_key": "11-04-2023",
    "order_nr": "AE1142438499",
    "wishlist_customer": "11687397",
    "wishlist_sku": "11136ACAEAAP",
    "wishlist_updated_at": "2023-04-09 01:30:53 UTC",
    "brand": "Seventy Five",
    "name": "Smart Watch W/ Dynamic Heart Rate & Multi Features",
    "activated_at": "2021-07-11 10:56:14 UTC",
    "season": "co",
    "color": "Blue",
    "department": "accessories",
    "category": "Watches",
    "subcategory": "Smart Watches",
    "product_gender": "Male",
    "age_group": "Adult",
    "price": "199",
    "price_level": "pl5",
    "merch_type": "Private",
    "occasion": "Casual",
    "short_description": "<ul><li>Processor - GR5515</li><li>Display: 1.69\" Color Screen/240*280</li><li>Battery Capacity: 190 mAh Lithium-ion battery</li><li>Built-in: Heart Rate Monitor</li><li>Waterproof: IP67</li><li>App name: Dafit</li><li>Working Time: 5 - 7 days</li><li>Reminder for incoming Call & SMS</li><li>Alarm/Anti-lost/Sedentary reminder</li><li>Time; date and week display/Power display/Find equipment</li><li>Pedometer/Sleeping monitor/Remote camera control/Music control</li><li>Message push: Skype; whatsapp; wechat; facebook; twitter etc.</li><li>Multiple sport modes/wake up screen by turn wrist</li><li>OS: Android 5.1 and above & IOS 10.0 and above</li><li>Charge the watch before first use</li></ul>",
    "namshi_description": "Smart Watch W/ Dynamic Heart Rate & Multi Features",
    "special_type": "Discounted",
    "world_tag": "Young Fashion",
    "customer_gender": "",
    "customer_generation": "1981-1996 Milennials",
    "customer_country_name": "United Arab Emirates",
    "RPC_gross_per_month": "239.5472131",
    "RPC_net_per_month": "230.5308197",
    "TPC_per_month": "1.459016393",
    "wishlist_customer_gender": "female",
    "wishlist_customer_generation": "Not Available",
    "wishlist_customer_country": "Saudi Arabia",
    "wishlist_rpc_gross": "20.84380952",
    "wishlist_rpc_net": "11.3952381",
    "wishlist_tpc": "0.142857143"
  },
  {
    "sku_config": "11136ACAEAAP",
    "fk_customer": "4487542",
    "order_date_key": "11-04-2023",
    "order_nr": "AE1142438499",
    "wishlist_customer": "16614242",
    "wishlist_sku": "11136ACAEAAP",
    "wishlist_updated_at": "2023-04-01 08:38:34 UTC",
    "brand": "Seventy Five",
    "name": "Smart Watch W/ Dynamic Heart Rate & Multi Features",
    "activated_at": "2021-07-11 10:56:14 UTC",
    "season": "co",
    "color": "Blue",
    "department": "accessories",
    "category": "Watches",
    "subcategory": "Smart Watches",
    "product_gender": "Male",
    "age_group": "Adult",
    "price": "199",
    "price_level": "pl5",
    "merch_type": "Private",
    "occasion": "Casual",
    "short_description": "<ul><li>Processor - GR5515</li><li>Display: 1.69\" Color Screen/240*280</li><li>Battery Capacity: 190 mAh Lithium-ion battery</li><li>Built-in: Heart Rate Monitor</li><li>Waterproof: IP67</li><li>App name: Dafit</li><li>Working Time: 5 - 7 days</li><li>Reminder for incoming Call & SMS</li><li>Alarm/Anti-lost/Sedentary reminder</li><li>Time; date and week display/Power display/Find equipment</li><li>Pedometer/Sleeping monitor/Remote camera control/Music control</li><li>Message push: Skype; whatsapp; wechat; facebook; twitter etc.</li><li>Multiple sport modes/wake up screen by turn wrist</li><li>OS: Android 5.1 and above & IOS 10.0 and above</li><li>Charge the watch before first use</li></ul>",
    "namshi_description": "Smart Watch W/ Dynamic Heart Rate & Multi Features",
    "special_type": "Discounted",
    "world_tag": "Young Fashion",
    "customer_gender": "",
    "customer_generation": "1981-1996 Milennials",
    "customer_country_name": "United Arab Emirates",
    "RPC_gross_per_month": "239.5472131",
    "RPC_net_per_month": "230.5308197",
    "TPC_per_month": "1.459016393",
    "wishlist_customer_gender": "female",
    "wishlist_customer_generation": "Not Available",
    "wishlist_customer_country": "Saudi Arabia",
    "wishlist_rpc_gross": "",
    "wishlist_rpc_net": "",
    "wishlist_tpc": ""
  },
  {
    "sku_config": "11136ACDSAHP",
    "fk_customer": "4487542",
    "order_date_key": "11-04-2023",
    "order_nr": "AE1142438499",
    "wishlist_customer": "7706014",
    "wishlist_sku": "11136ACDSAHP",
    "wishlist_updated_at": "2023-04-04 01:29:40 UTC",
    "brand": "Seventy Five",
    "name": "Smart Watch With Health And Fitness Features",
    "activated_at": "2021-09-08 07:21:13 UTC",
    "season": "co",
    "color": "Black",
    "department": "accessories",
    "category": "Watches",
    "subcategory": "Smart Watches",
    "product_gender": "Male",
    "age_group": "Adult",
    "price": "199",
    "price_level": "pl5",
    "merch_type": "Private",
    "occasion": "Casual",
    "short_description": "<ul><li>Durable and lightweight gel silicon wrist straps</li><li>Smart watch with display 1.3 inch</li><li>HD Colour Screen 240 x 240 Resolution</li><li>Battery Capacity: 200mAH</li><li>Water proof level: IP67 equivalent to 1 m</li></ul>",
    "namshi_description": "Smart Watch With Health And Fitness Features",
    "special_type": "Discounted",
    "world_tag": "Young Fashion",
    "customer_gender": "",
    "customer_generation": "1981-1996 Milennials",
    "customer_country_name": "United Arab Emirates",
    "RPC_gross_per_month": "239.5472131",
    "RPC_net_per_month": "230.5308197",
    "TPC_per_month": "1.459016393",
    "wishlist_customer_gender": "female",
    "wishlist_customer_generation": "1981-1996 Milennials",
    "wishlist_customer_country": "Saudi Arabia",
    "wishlist_rpc_gross": "204.6",
    "wishlist_rpc_net": "71.60142857",
    "wishlist_tpc": "0.321428571"
  },
  {
    "sku_config": "11136ACDSAHP",
    "fk_customer": "4487542",
    "order_date_key": "11-04-2023",
    "order_nr": "AE1142438499",
    "wishlist_customer": "590797",
    "wishlist_sku": "11136ACDSAHP",
    "wishlist_updated_at": "2023-04-03 17:23:08 UTC",
    "brand": "Seventy Five",
    "name": "Smart Watch With Health And Fitness Features",
    "activated_at": "2021-09-08 07:21:13 UTC",
    "season": "co",
    "color": "Black",
    "department": "accessories",
    "category": "Watches",
    "subcategory": "Smart Watches",
    "product_gender": "Male",
    "age_group": "Adult",
    "price": "199",
    "price_level": "pl5",
    "merch_type": "Private",
    "occasion": "Casual",
    "short_description": "<ul><li>Durable and lightweight gel silicon wrist straps</li><li>Smart watch with display 1.3 inch</li><li>HD Colour Screen 240 x 240 Resolution</li><li>Battery Capacity: 200mAH</li><li>Water proof level: IP67 equivalent to 1 m</li></ul>",
    "namshi_description": "Smart Watch With Health And Fitness Features",
    "special_type": "Discounted",
    "world_tag": "Young Fashion",
    "customer_gender": "",
    "customer_generation": "1981-1996 Milennials",
    "customer_country_name": "United Arab Emirates",
    "RPC_gross_per_month": "239.5472131",
    "RPC_net_per_month": "230.5308197",
    "TPC_per_month": "1.459016393",
    "wishlist_customer_gender": "female",
    "wishlist_customer_generation": "1997-2012 Generation Z",
    "wishlist_customer_country": "Saudi Arabia",
    "wishlist_rpc_gross": "165.6506742",
    "wishlist_rpc_net": "115.4519101",
    "wishlist_tpc": "0.494382022"
  },
  {
    "sku_config": "11136ACAEAAP",
    "fk_customer": "4487542",
    "order_date_key": "11-04-2023",
    "order_nr": "AE1142438499",
    "wishlist_customer": "2876361",
    "wishlist_sku": "11136ACAEAAP",
    "wishlist_updated_at": "2023-04-08 05:09:22 UTC",
    "brand": "Seventy Five",
    "name": "Smart Watch W/ Dynamic Heart Rate & Multi Features",
    "activated_at": "2021-07-11 10:56:14 UTC",
    "season": "co",
    "color": "Blue",
    "department": "accessories",
    "category": "Watches",
    "subcategory": "Smart Watches",
    "product_gender": "Male",
    "age_group": "Adult",
    "price": "199",
    "price_level": "pl5",
    "merch_type": "Private",
    "occasion": "Casual",
    "short_description": "<ul><li>Processor - GR5515</li><li>Display: 1.69\" Color Screen/240*280</li><li>Battery Capacity: 190 mAh Lithium-ion battery</li><li>Built-in: Heart Rate Monitor</li><li>Waterproof: IP67</li><li>App name: Dafit</li><li>Working Time: 5 - 7 days</li><li>Reminder for incoming Call & SMS</li><li>Alarm/Anti-lost/Sedentary reminder</li><li>Time; date and week display/Power display/Find equipment</li><li>Pedometer/Sleeping monitor/Remote camera control/Music control</li><li>Message push: Skype; whatsapp; wechat; facebook; twitter etc.</li><li>Multiple sport modes/wake up screen by turn wrist</li><li>OS: Android 5.1 and above & IOS 10.0 and above</li><li>Charge the watch before first use</li></ul>",
    "namshi_description": "Smart Watch W/ Dynamic Heart Rate & Multi Features",
    "special_type": "Discounted",
    "world_tag": "Young Fashion",
    "customer_gender": "",
    "customer_generation": "1981-1996 Milennials",
    "customer_country_name": "United Arab Emirates",
    "RPC_gross_per_month": "239.5472131",
    "RPC_net_per_month": "230.5308197",
    "TPC_per_month": "1.459016393",
    "wishlist_customer_gender": "",
    "wishlist_customer_generation": "Not Available",
    "wishlist_customer_country": "Oman",
    "wishlist_rpc_gross": "73.31352113",
    "wishlist_rpc_net": "62.04577465",
    "wishlist_tpc": "0.169014085"
  },
  {
    "sku_config": "11136ACDSAHP",
    "fk_customer": "4487542",
    "order_date_key": "11-04-2023",
    "order_nr": "AE1142438499",
    "wishlist_customer": "10975892",
    "wishlist_sku": "11136ACDSAHP",
    "wishlist_updated_at": "2023-04-03 03:00:31 UTC",
    "brand": "Seventy Five",
    "name": "Smart Watch With Health And Fitness Features",
    "activated_at": "2021-09-08 07:21:13 UTC",
    "season": "co",
    "color": "Black",
    "department": "accessories",
    "category": "Watches",
    "subcategory": "Smart Watches",
    "product_gender": "Male",
    "age_group": "Adult",
    "price": "199",
    "price_level": "pl5",
    "merch_type": "Private",
    "occasion": "Casual",
    "short_description": "<ul><li>Durable and lightweight gel silicon wrist straps</li><li>Smart watch with display 1.3 inch</li><li>HD Colour Screen 240 x 240 Resolution</li><li>Battery Capacity: 200mAH</li><li>Water proof level: IP67 equivalent to 1 m</li></ul>",
    "namshi_description": "Smart Watch With Health And Fitness Features",
    "special_type": "Discounted",
    "world_tag": "Young Fashion",
    "customer_gender": "",
    "customer_generation": "1981-1996 Milennials",
    "customer_country_name": "United Arab Emirates",
    "RPC_gross_per_month": "239.5472131",
    "RPC_net_per_month": "230.5308197",
    "TPC_per_month": "1.459016393",
    "wishlist_customer_gender": "",
    "wishlist_customer_generation": "Not Available",
    "wishlist_customer_country": "Saudi Arabia",
    "wishlist_rpc_gross": "75.19",
    "wishlist_rpc_net": "36.02",
    "wishlist_tpc": "1"
  },
  {
    "sku_config": "11096SH49ZKP",
    "fk_customer": "5404907",
    "order_date_key": "10-04-2023",
    "order_nr": "AE1149911891",
    "wishlist_customer": "6856757",
    "wishlist_sku": "11096SH49ZKP",
    "wishlist_updated_at": "2023-04-10 04:05:53 UTC",
    "brand": "Ginger",
    "name": "Mid Heel Barely There Sandal",
    "activated_at": "2019-09-18 10:40:22 UTC",
    "season": "co",
    "color": "White",
    "department": "shoes",
    "category": "Sandals",
    "subcategory": "Sandals",
    "product_gender": "Female",
    "age_group": "Adult",
    "price": "159",
    "price_level": "pl3",
    "merch_type": "Private",
    "occasion": "Party",
    "short_description": "<ul><li>Durable and strappy synthetic upper</li><li>Slightly cushioned footbed for comfort</li><li>Mid-heel for added height and style</li><li>Patterned sturdy outsole for durability</li></ul>",
    "namshi_description": "Mid Heel Barely There Sandal",
    "special_type": "Discounted",
    "world_tag": "Young Fashion",
    "customer_gender": "female",
    "customer_generation": "Not Available",
    "customer_country_name": "United Arab Emirates",
    "RPC_gross_per_month": "59.25125",
    "RPC_net_per_month": "49.79892857",
    "TPC_per_month": "0.321428571",
    "wishlist_customer_gender": "",
    "wishlist_customer_generation": "1997-2012 Generation Z",
    "wishlist_customer_country": "Saudi Arabia",
    "wishlist_rpc_gross": "221.7826087",
    "wishlist_rpc_net": "221.7826087",
    "wishlist_tpc": "0.260869565"
  },
  {
    "sku_config": "29832AC88WPP",
    "fk_customer": "8490410",
    "order_date_key": "10-04-2023",
    "order_nr": "AE1146719882",
    "wishlist_customer": "7053768",
    "wishlist_sku": "29832AC88WPP",
    "wishlist_updated_at": "2023-04-01 14:24:47 UTC",
    "brand": "Mac Cosmetics",
    "name": "Prep + Prime Fix+ Makeup Spray 100ml",
    "activated_at": "2019-04-28 11:25:09 UTC",
    "season": "co",
    "color": "Clear",
    "department": "beauty",
    "category": "Skin Care",
    "subcategory": "Facial Cleansers",
    "product_gender": "Female",
    "age_group": "Adult",
    "price": "115",
    "price_level": "pl4",
    "merch_type": "Premium",
    "occasion": "Casual",
    "short_description": "<p><font size=\"3\">A lightweight mist of water packed with vitamins and minerals; infused with a blend of green tea; chamomile and cucumber to gently soothe and refresh the skin. Gives an instant boost of hydration while delivering a soft sheen to refresh and finish makeup. This holy grail of hydrating mists can be used with other products in near-endless ways to improve the wear of makeup; or moisturize and soothe tired skin. A delicious twist in a permanent romantic rose scent; calming lavender scent; or creamy coconut scent.<br>-Packaging may vary.<br>-Soothes; hydrates and refreshes skin.<br>- Sets and improves the quality wear of makeup up to 12 hours.<br>- Dermatologist tested; Ophthalmologist tested and Non-acnegenic.</font></p><br><li>How to use: <br>-Hold bottle 12 inches away from face and spray evenly. Use alone or to finish makeup.<br>-  For face products; apply your favourite powder foundation and lightly mist all over face to set and hydrate.<br>- For colour products; apply your favourite eye shadow or pigment to your preferred brush; lightly mist bristles and sweep across lids for an intensified shadow look.</li>",
    "namshi_description": "Prep + Prime Fix+ Makeup Spray 100ml",
    "special_type": "Full Price",
    "world_tag": "",
    "customer_gender": "",
    "customer_generation": "1981-1996 Milennials",
    "customer_country_name": "United Arab Emirates",
    "RPC_gross_per_month": "615.7114286",
    "RPC_net_per_month": "534.654",
    "TPC_per_month": "2.828571429",
    "wishlist_customer_gender": "female",
    "wishlist_customer_generation": "1965-1980 Generation X",
    "wishlist_customer_country": "Oman",
    "wishlist_rpc_gross": "227.1064865",
    "wishlist_rpc_net": "227.1064865",
    "wishlist_tpc": "0.918918919"
  },
  {
    "sku_config": "14384ACRZOZP",
    "fk_customer": "5105620",
    "order_date_key": "10-04-2023",
    "order_nr": "AE1147942326",
    "wishlist_customer": "15346193",
    "wishlist_sku": "14384ACRZOZP",
    "wishlist_updated_at": "2023-04-10 04:15:46 UTC",
    "brand": "Fossil",
    "name": "Steel Strap Analog Watch",
    "activated_at": "2021-11-16 08:00:16 UTC",
    "season": "aw22",
    "color": "Metallic",
    "department": "accessories",
    "category": "Watches",
    "subcategory": "Analog Watches",
    "product_gender": "Female",
    "age_group": "Adult",
    "price": "614",
    "price_level": "pl8",
    "merch_type": "General",
    "occasion": "Casual",
    "short_description": "<ul><li>Durable silver-tone metal linked bracelet</li><li>Round dial set on stainless steel case</li><li>Marked indices and date window</li><li>Triple arm Swiss movement</li><li>Secure fold over closure</li><li>Packed in a Fossil branded box</li><li>Case dimensions: 38mm</li></ul>",
    "namshi_description": "Steel Strap Analog Watch",
    "special_type": "Discounted",
    "world_tag": "Casual",
    "customer_gender": "female",
    "customer_generation": "Not Available",
    "customer_country_name": "United Arab Emirates",
    "RPC_gross_per_month": "1057.826939",
    "RPC_net_per_month": "555.4391837",
    "TPC_per_month": "2.714285714",
    "wishlist_customer_gender": "",
    "wishlist_customer_generation": "1981-1996 Milennials",
    "wishlist_customer_country": "Saudi Arabia",
    "wishlist_rpc_gross": "281.7528571",
    "wishlist_rpc_net": "161.53",
    "wishlist_tpc": "0.571428571"
  },
  {
    "sku_config": "13288ATJXEXP",
    "fk_customer": "14316689",
    "order_date_key": "10-04-2023",
    "order_nr": "AE1144017775",
    "wishlist_customer": "7530428",
    "wishlist_sku": "13288ATJXEXP",
    "wishlist_updated_at": "2023-04-07 21:37:54 UTC",
    "brand": "Ella",
    "name": "Printed Shirt",
    "activated_at": "2023-02-13 15:10:25 UTC",
    "season": "ss23",
    "color": "Prints",
    "department": "clothing",
    "category": "Tops",
    "subcategory": "Shirts & Blouses",
    "product_gender": "Female",
    "age_group": "Adult",
    "price": "119",
    "price_level": "pl4",
    "merch_type": "Private",
    "occasion": "Casual",
    "short_description": "<p><font size=”3”><center>This shirt is designed to give you a casual yet comfortable everyday look.</center></p></font><br><li>Soft and comfortable polyester fabric</li><li>Contrast graphic prints all over</li><li>Long sleeves with buttoned cuffs</li><li>Broad; fluid panel overlays to yoke</li><li>Secure button down closure to front</li><li>Each item sold separately</li>",
    "namshi_description": "Printed Shirt",
    "special_type": "Discounted",
    "world_tag": "Smart",
    "customer_gender": "female",
    "customer_generation": "Not Available",
    "customer_country_name": "United Arab Emirates",
    "RPC_gross_per_month": "373.3318182",
    "RPC_net_per_month": "373.3318182",
    "TPC_per_month": "0.545454545",
    "wishlist_customer_gender": "",
    "wishlist_customer_generation": "1997-2012 Generation Z",
    "wishlist_customer_country": "United Arab Emirates",
    "wishlist_rpc_gross": "",
    "wishlist_rpc_net": "",
    "wishlist_tpc": ""
  },
  {
    "sku_config": "72704SHTCZYP",
    "fk_customer": "6133130",
    "order_date_key": "10-04-2023",
    "order_nr": "AE1149153401",
    "wishlist_customer": "8995675",
    "wishlist_sku": "72704SHTCZYP",
    "wishlist_updated_at": "2023-04-08 09:58:44 UTC",
    "brand": "Nike",
    "name": "Infant Star Runner 3",
    "activated_at": "2021-10-17 08:15:27 UTC",
    "season": "co",
    "color": "Black",
    "department": "shoes",
    "category": "Sports Shoes",
    "subcategory": "Low - Top",
    "product_gender": "Male",
    "age_group": "kids",
    "price": "179",
    "price_level": "pl3",
    "merch_type": "Sports",
    "occasion": "performance",
    "short_description": "<ul><li>Lightweight; breathable textile mesh and leather upper</li><li>Secure velcro closure</li><li>Cushioning around the ankle and on the tongue feels plush</li><li>Rubber sole provides durable traction; Grooves on the sole make it flexible</li><li>Contrast Nike signature branding</li></ul>",
    "namshi_description": "Infant Star Runner 3",
    "special_type": "Discounted",
    "world_tag": "Performance",
    "customer_gender": "female",
    "customer_generation": "1981-1996 Milennials",
    "customer_country_name": "United Arab Emirates",
    "RPC_gross_per_month": "130.9830556",
    "RPC_net_per_month": "79.18055556",
    "TPC_per_month": "0.583333333",
    "wishlist_customer_gender": "",
    "wishlist_customer_generation": "Not Available",
    "wishlist_customer_country": "Kuwait",
    "wishlist_rpc_gross": "462.3276471",
    "wishlist_rpc_net": "338.6588235",
    "wishlist_tpc": "1.176470588"
  },
  {
    "sku_config": "70680SHLNTUP",
    "fk_customer": "15420932",
    "order_date_key": "10-04-2023",
    "order_nr": "AE1146639590",
    "wishlist_customer": "14608160",
    "wishlist_sku": "70680SHLNTUP",
    "wishlist_updated_at": "2023-04-04 17:26:13 UTC",
    "brand": "Under Armour",
    "name": "Charged Pursuit 3",
    "activated_at": "2023-02-18 06:55:47 UTC",
    "season": "ss23",
    "color": "Navy",
    "department": "shoes",
    "category": "Sports Shoes",
    "subcategory": "Low - Top",
    "product_gender": "Male",
    "age_group": "Adult",
    "price": "349",
    "price_level": "pl5",
    "merch_type": "Sports",
    "occasion": "performance",
    "short_description": "<p><font size=\"3\"><center>You don't have to run far to feel the benefits of training. Slip on these Under Armour shoes and you're only a few miles away from a good mood.</center></p></font><br><li>Performance mesh upper for lightweight breathability</li><li>Eyelets with secure lace-up closure</li><li>Foam padding placed around your ankle collar for comfort</li><li>Deluxe foam sock liner molds to your foot for added underfoot comfort</li><li>Charged Cushioning midsole uses compression molded foam for ultimate responsiveness and durability</li><li>Durable outsole pattern for flex and traction</li><li>Under Armour signature branding detail</li>",
    "namshi_description": "Charged Pursuit 3",
    "special_type": "Discounted",
    "world_tag": "Performance",
    "customer_gender": "male",
    "customer_generation": "Not Available",
    "customer_country_name": "United Arab Emirates",
    "RPC_gross_per_month": "524.5557143",
    "RPC_net_per_month": "222.72",
    "TPC_per_month": "2.285714286",
    "wishlist_customer_gender": "male",
    "wishlist_customer_generation": "Not Available",
    "wishlist_customer_country": "Qatar",
    "wishlist_rpc_gross": "461.726",
    "wishlist_rpc_net": "278.798",
    "wishlist_tpc": "0.6"
  },
  {
    "sku_config": "20000SHFADTP",
    "fk_customer": "2356867",
    "order_date_key": "10-04-2023",
    "order_nr": "AE1142530862",
    "wishlist_customer": "16740094",
    "wishlist_sku": "20000SHFADTP",
    "wishlist_updated_at": "2023-04-07 00:51:07 UTC",
    "brand": "Puma",
    "name": "X-Ray Speed Lite",
    "activated_at": "2023-01-24 13:45:20 UTC",
    "season": "aw22",
    "color": "black",
    "department": "shoes",
    "category": "Sneakers",
    "subcategory": "Low - Top",
    "product_gender": "Male",
    "age_group": "Adult",
    "price": "299",
    "price_level": "pl5",
    "merch_type": "Sports",
    "occasion": "lifestyle",
    "short_description": "<p><font size=\"3\"><center>You've got the skills; you've got the game. Now show them off with this Puma shoes.</center></p></font><br><li>Mesh upper with suede and synthetic leather overlays</li><li>Eyelets with secure lace-up closure</li><li>Soft Foam+ sockliner provides optimal step-in comfort</li><li>IMEVA midsole for lightweight cushioning</li><li>Rubber outsole provides traction and grip</li><li>Puma signature branding detail</li>",
    "namshi_description": "X-Ray Speed Lite",
    "special_type": "Discounted",
    "world_tag": "Performance",
    "customer_gender": "female",
    "customer_generation": "1981-1996 Milennials",
    "customer_country_name": "United Arab Emirates",
    "RPC_gross_per_month": "379.5572727",
    "RPC_net_per_month": "205.9518182",
    "TPC_per_month": "1.597402597",
    "wishlist_customer_gender": "",
    "wishlist_customer_generation": "Not Available",
    "wishlist_customer_country": "United Arab Emirates",
    "wishlist_rpc_gross": "",
    "wishlist_rpc_net": "",
    "wishlist_tpc": ""
  },
  {
    "sku_config": "88072SH21XVP",
    "fk_customer": "9320823",
    "order_date_key": "10-04-2023",
    "order_nr": "AE1144930090",
    "wishlist_customer": "14769829",
    "wishlist_sku": "88072SH21XVP",
    "wishlist_updated_at": "2023-04-09 05:11:42 UTC",
    "brand": "Vans",
    "name": "Old Skool",
    "activated_at": "2019-07-08 07:10:28 UTC",
    "season": "co",
    "color": "White",
    "department": "shoes",
    "category": "Sneakers",
    "subcategory": "Low - Top",
    "product_gender": "Male",
    "age_group": "Adult",
    "price": "329",
    "price_level": "pl6",
    "merch_type": "Sports",
    "occasion": "lifestyle",
    "short_description": "<ul><li>Woven canvas upper with genuine leather overlays</li><li>Eyelets with secure lace-up closure</li><li>Slightly cushioned footbed for comfort</li><li>Waffle patterned rubber outsole for better grip</li><li>Vans signature print branding</li></ul>",
    "namshi_description": "Old Skool",
    "special_type": "Discounted",
    "world_tag": "Skate",
    "customer_gender": "female",
    "customer_generation": "Not Available",
    "customer_country_name": "United Arab Emirates",
    "RPC_gross_per_month": "12.66666667",
    "RPC_net_per_month": "12.66666667",
    "TPC_per_month": "0.1",
    "wishlist_customer_gender": "male",
    "wishlist_customer_generation": "Not Available",
    "wishlist_customer_country": "United Arab Emirates",
    "wishlist_rpc_gross": "211.94",
    "wishlist_rpc_net": "142.6277778",
    "wishlist_tpc": "1.666666667"
  },
  {
    "sku_config": "72704SHQGOIP",
    "fk_customer": "17147186",
    "order_date_key": "10-04-2023",
    "order_nr": "AE1142635317",
    "wishlist_customer": "5949436",
    "wishlist_sku": "72704SHQGOIP",
    "wishlist_updated_at": "2023-04-10 11:01:50 UTC",
    "brand": "Nike",
    "name": "Downshifter 12",
    "activated_at": "2022-11-24 13:40:19 UTC",
    "season": "co",
    "color": "Black",
    "department": "shoes",
    "category": "Sports Shoes",
    "subcategory": "Low - Top",
    "product_gender": "Female",
    "age_group": "Adult",
    "price": "350",
    "price_level": "pl5",
    "merch_type": "Sports",
    "occasion": "performance",
    "short_description": "<p><font size=\"3\"><center>Whether you're playing a game of tig or warming up for athletic training; feel confident when you pull on the Nike Downshifter 12.</center></p></font><br><li>Lightweight and breathable mesh upper</li><li>Eyelets with secure lace-up closure</li><li>Supersoft foam midsole helps cushion your foot with every step</li><li>Pull tab on heel top for easy on-off</li><li>Patterned rubber outsole for traction and durability</li><li>Tonal Nike swoosh branding</li>",
    "namshi_description": "Downshifter 12",
    "special_type": "Discounted",
    "world_tag": "Performance",
    "customer_gender": "",
    "customer_generation": "Not Available",
    "customer_country_name": "United Arab Emirates",
    "RPC_gross_per_month": "",
    "RPC_net_per_month": "",
    "TPC_per_month": "",
    "wishlist_customer_gender": "female",
    "wishlist_customer_generation": "Not Available",
    "wishlist_customer_country": "Kuwait",
    "wishlist_rpc_gross": "91.98846154",
    "wishlist_rpc_net": "88.43230769",
    "wishlist_tpc": "0.076923077"
  },
  {
    "sku_config": "14448SHKNKRP",
    "fk_customer": "12708030",
    "order_date_key": "10-04-2023",
    "order_nr": "AE1148968656",
    "wishlist_customer": "8995675",
    "wishlist_sku": "14448SHKNKRP",
    "wishlist_updated_at": "2023-04-08 10:12:27 UTC",
    "brand": "Adidas",
    "name": "Kids Duramo 10 K  ",
    "activated_at": "2022-08-29 13:45:36 UTC",
    "season": "co",
    "color": "grey",
    "department": "shoes",
    "category": "Sports Shoes",
    "subcategory": "Low - Top",
    "product_gender": "Female",
    "age_group": "kids",
    "price": "229",
    "price_level": "pl4",
    "merch_type": "Sports",
    "occasion": "performance",
    "short_description": "",
    "namshi_description": "Kids Duramo 10 K  ",
    "special_type": "Discounted",
    "world_tag": "Performance",
    "customer_gender": "female",
    "customer_generation": "1981-1996 Milennials",
    "customer_country_name": "United Arab Emirates",
    "RPC_gross_per_month": "119.54",
    "RPC_net_per_month": "94.33",
    "TPC_per_month": "0.470588235",
    "wishlist_customer_gender": "",
    "wishlist_customer_generation": "Not Available",
    "wishlist_customer_country": "Kuwait",
    "wishlist_rpc_gross": "462.3276471",
    "wishlist_rpc_net": "338.6588235",
    "wishlist_tpc": "1.176470588"
  },
  {
    "sku_config": "20000SHFADTP",
    "fk_customer": "2356867",
    "order_date_key": "10-04-2023",
    "order_nr": "AE1142530862",
    "wishlist_customer": "17074748",
    "wishlist_sku": "20000SHFADTP",
    "wishlist_updated_at": "2023-04-03 21:03:19 UTC",
    "brand": "Puma",
    "name": "X-Ray Speed Lite",
    "activated_at": "2023-01-24 13:45:20 UTC",
    "season": "aw22",
    "color": "black",
    "department": "shoes",
    "category": "Sneakers",
    "subcategory": "Low - Top",
    "product_gender": "Male",
    "age_group": "Adult",
    "price": "299",
    "price_level": "pl5",
    "merch_type": "Sports",
    "occasion": "lifestyle",
    "short_description": "<p><font size=\"3\"><center>You've got the skills; you've got the game. Now show them off with this Puma shoes.</center></p></font><br><li>Mesh upper with suede and synthetic leather overlays</li><li>Eyelets with secure lace-up closure</li><li>Soft Foam+ sockliner provides optimal step-in comfort</li><li>IMEVA midsole for lightweight cushioning</li><li>Rubber outsole provides traction and grip</li><li>Puma signature branding detail</li>",
    "namshi_description": "X-Ray Speed Lite",
    "special_type": "Discounted",
    "world_tag": "Performance",
    "customer_gender": "female",
    "customer_generation": "1981-1996 Milennials",
    "customer_country_name": "United Arab Emirates",
    "RPC_gross_per_month": "379.5572727",
    "RPC_net_per_month": "205.9518182",
    "TPC_per_month": "1.597402597",
    "wishlist_customer_gender": "",
    "wishlist_customer_generation": "1981-1996 Milennials",
    "wishlist_customer_country": "United Arab Emirates",
    "wishlist_rpc_gross": "",
    "wishlist_rpc_net": "",
    "wishlist_tpc": ""
  },
  {
    "sku_config": "40992SHLMRBP",
    "fk_customer": "6231222",
    "order_date_key": "10-04-2023",
    "order_nr": "AE1148115638",
    "wishlist_customer": "6188315",
    "wishlist_sku": "40992SHLMRBP",
    "wishlist_updated_at": "2023-04-04 05:28:44 UTC",
    "brand": "Namshi X",
    "name": "Diamante Ankle Strap Pointed Pump",
    "activated_at": "2023-03-17 13:00:20 UTC",
    "season": "ss23",
    "color": "White",
    "department": "shoes",
    "category": "Pumps",
    "subcategory": "Pumps",
    "product_gender": "Female",
    "age_group": "Adult",
    "price": "219",
    "price_level": "pl5",
    "merch_type": "Private",
    "occasion": "Party",
    "short_description": "<p><font size=\"3\"><center>A slight sparkle ensures these pumps make an entrance.</center></p></font><br><li>Shiny and lightweight textile upper</li><li>Faux stones embellished straps</li><li>Ankle strap with adjustable pin-buckle closure</li><li>Cushioned footbed for added comfort</li><li>Mid-heel for added height and style</li><li>Patterned synthetic outsole for better grip</li>",
    "namshi_description": "Diamante Ankle Strap Pointed Pump",
    "special_type": "Full Price",
    "world_tag": "",
    "customer_gender": "",
    "customer_generation": "Not Available",
    "customer_country_name": "United Arab Emirates",
    "RPC_gross_per_month": "37.81897959",
    "RPC_net_per_month": "20.50612245",
    "TPC_per_month": "0.142857143",
    "wishlist_customer_gender": "",
    "wishlist_customer_generation": "Not Available",
    "wishlist_customer_country": "Saudi Arabia",
    "wishlist_rpc_gross": "135.5545946",
    "wishlist_rpc_net": "124.0721622",
    "wishlist_tpc": "0.405405405"
  },
  {
    "sku_config": "GI640AT65JFY",
    "fk_customer": "15867017",
    "order_date_key": "10-04-2023",
    "order_nr": "AE114404303",
    "wishlist_customer": "11999378",
    "wishlist_sku": "GI640AT65JFY",
    "wishlist_updated_at": "2023-04-02 20:56:49 UTC",
    "brand": "Ginger Basics",
    "name": "Essential Crew Neck T-Shirt",
    "activated_at": "2018-04-09 13:56:47 UTC",
    "season": "noos",
    "color": "white",
    "department": "clothing",
    "category": "T-Shirts & Vests",
    "subcategory": "T-Shirts",
    "product_gender": "Female",
    "age_group": "Adult",
    "price": "25",
    "price_level": "pl1",
    "merch_type": "Private",
    "occasion": "Casual",
    "short_description": "<ul><li>Each item sold separately</li></ul>",
    "namshi_description": "Essential Crew Neck T-Shirt",
    "special_type": "Discounted",
    "world_tag": "Essentials",
    "customer_gender": "female",
    "customer_generation": "Not Available",
    "customer_country_name": "United Arab Emirates",
    "RPC_gross_per_month": "1481.02",
    "RPC_net_per_month": "1358.68",
    "TPC_per_month": "5",
    "wishlist_customer_gender": "female",
    "wishlist_customer_generation": "Not Available",
    "wishlist_customer_country": "Saudi Arabia",
    "wishlist_rpc_gross": "48.63352941",
    "wishlist_rpc_net": "46.39647059",
    "wishlist_tpc": "0.235294118"
  },
  {
    "sku_config": "86864AC46ZVP",
    "fk_customer": "4326525",
    "order_date_key": "10-04-2023",
    "order_nr": "AE114379170",
    "wishlist_customer": "14807827",
    "wishlist_sku": "86864AC46ZVP",
    "wishlist_updated_at": "2023-04-09 10:25:03 UTC",
    "brand": "Vichy",
    "name": "24hr Deodorant For Very Sensitive Or Depilated Skin",
    "activated_at": "2020-10-14 15:00:35 UTC",
    "season": "co",
    "color": "white",
    "department": "beauty",
    "category": "Bath & Body",
    "subcategory": "Deodorants",
    "product_gender": "Female",
    "age_group": "Adult",
    "price": "91",
    "price_level": "pl3",
    "merch_type": "General",
    "occasion": "Casual",
    "short_description": "<p><font size=\"3\">Stick format; free from aluminum salts; perfectly adapted to all skin types; even sensitive. Zinc ricinoleate; a deodorant and antibacterial active ingredient that absorbs odours; makes this treatment an effective ultra-deodorant for freshness and a sensation of comfort that lasts all day.</font><br><br><li>24-hour deodorant efficacy.<br><li>How to use: Apply daily to clean; dry armpits.</p>",
    "namshi_description": "24hr Deodorant For Very Sensitive Or Depilated Skin",
    "special_type": "Discounted",
    "world_tag": "",
    "customer_gender": "",
    "customer_generation": "Not Available",
    "customer_country_name": "United Arab Emirates",
    "RPC_gross_per_month": "37.12596774",
    "RPC_net_per_month": "37.12596774",
    "TPC_per_month": "0.080645161",
    "wishlist_customer_gender": "female",
    "wishlist_customer_generation": "1981-1996 Milennials",
    "wishlist_customer_country": "United Arab Emirates",
    "wishlist_rpc_gross": "72.38",
    "wishlist_rpc_net": "43.095",
    "wishlist_tpc": "0.5"
  },
  {
    "sku_config": "12232SHJOEZP",
    "fk_customer": "16744010",
    "order_date_key": "10-04-2023",
    "order_nr": "AE1149225403",
    "wishlist_customer": "16090190",
    "wishlist_sku": "12232SHJOEZP",
    "wishlist_updated_at": "2023-04-08 05:02:31 UTC",
    "brand": "Tommy Hilfiger",
    "name": "Logo Low Top Sneakers",
    "activated_at": "2023-02-24 07:45:16 UTC",
    "season": "ss23",
    "color": "Navy",
    "department": "shoes",
    "category": "Sneakers",
    "subcategory": "Low-Top Sneakers",
    "product_gender": "Male",
    "age_group": "Adult",
    "price": "409",
    "price_level": "pl7",
    "merch_type": "Premium",
    "occasion": "Casual",
    "short_description": "<p><font size=”3”><center>Elevate your shoe collection with this pair of low-top leather sneakers from Tommy Hilfiger.</center></p></font><br><li>Durable and lightweight canvas upper</li><li>Eyelets with secure lace up closure</li><li>Cushioned footbed for added comfort</li><li>Thick protective foxing to midsole</li><li>Patterned synthetic outsole for better grip</li><li>Contrast Tommy Hilfiger signature branding</li>",
    "namshi_description": "Logo Low Top Sneakers",
    "special_type": "Discounted",
    "world_tag": "Smart",
    "customer_gender": "",
    "customer_generation": "1981-1996 Milennials",
    "customer_country_name": "United Arab Emirates",
    "RPC_gross_per_month": "",
    "RPC_net_per_month": "",
    "TPC_per_month": "",
    "wishlist_customer_gender": "",
    "wishlist_customer_generation": "1965-1980 Generation X",
    "wishlist_customer_country": "United Arab Emirates",
    "wishlist_rpc_gross": "73.008",
    "wishlist_rpc_net": "73.008",
    "wishlist_tpc": "0.4"
  },
  {
    "sku_config": "14448SHYVURP",
    "fk_customer": "1145667",
    "order_date_key": "10-04-2023",
    "order_nr": "AE114377509",
    "wishlist_customer": "15673765",
    "wishlist_sku": "14448SHYVURP",
    "wishlist_updated_at": "2023-04-10 06:48:16 UTC",
    "brand": "Adidas",
    "name": "Adilette Sandals",
    "activated_at": "2023-03-02 12:35:10 UTC",
    "season": "core",
    "color": "black",
    "department": "shoes",
    "category": "Sandals",
    "subcategory": "Casual Sandals",
    "product_gender": "Male",
    "age_group": "Adult",
    "price": "199",
    "price_level": "pl4",
    "merch_type": "Sports",
    "occasion": "lifestyle",
    "short_description": "<p><font size=\"3\"><center>Minimalist casual flip flops perfect for everyday wear.</center></p></font><br><li>Smooth and durable textile upper</li><li>Open  toe with secure velcro closure</li><li>Soft Cloud foam footbed for comfort</li><li>Patterned sturdy EVA outsole for traction</li><li>adidas Originals signature and trefoil branding detail</li>",
    "namshi_description": "Adilette Sandals",
    "special_type": "Discounted",
    "world_tag": "Performance",
    "customer_gender": "",
    "customer_generation": "1965-1980 Generation X",
    "customer_country_name": "United Arab Emirates",
    "RPC_gross_per_month": "405.8388043",
    "RPC_net_per_month": "296.8665217",
    "TPC_per_month": "1.847826087",
    "wishlist_customer_gender": "female",
    "wishlist_customer_generation": "1981-1996 Milennials",
    "wishlist_customer_country": "United Arab Emirates",
    "wishlist_rpc_gross": "132.855",
    "wishlist_rpc_net": "132.855",
    "wishlist_tpc": "0.5"
  },
  {
    "sku_config": "40992SHLMRBP",
    "fk_customer": "6231222",
    "order_date_key": "10-04-2023",
    "order_nr": "AE1148115638",
    "wishlist_customer": "15681053",
    "wishlist_sku": "40992SHLMRBP",
    "wishlist_updated_at": "2023-04-05 10:19:00 UTC",
    "brand": "Namshi X",
    "name": "Diamante Ankle Strap Pointed Pump",
    "activated_at": "2023-03-17 13:00:20 UTC",
    "season": "ss23",
    "color": "White",
    "department": "shoes",
    "category": "Pumps",
    "subcategory": "Pumps",
    "product_gender": "Female",
    "age_group": "Adult",
    "price": "219",
    "price_level": "pl5",
    "merch_type": "Private",
    "occasion": "Party",
    "short_description": "<p><font size=\"3\"><center>A slight sparkle ensures these pumps make an entrance.</center></p></font><br><li>Shiny and lightweight textile upper</li><li>Faux stones embellished straps</li><li>Ankle strap with adjustable pin-buckle closure</li><li>Cushioned footbed for added comfort</li><li>Mid-heel for added height and style</li><li>Patterned synthetic outsole for better grip</li>",
    "namshi_description": "Diamante Ankle Strap Pointed Pump",
    "special_type": "Full Price",
    "world_tag": "",
    "customer_gender": "",
    "customer_generation": "Not Available",
    "customer_country_name": "United Arab Emirates",
    "RPC_gross_per_month": "37.81897959",
    "RPC_net_per_month": "20.50612245",
    "TPC_per_month": "0.142857143",
    "wishlist_customer_gender": "female",
    "wishlist_customer_generation": "Not Available",
    "wishlist_customer_country": "Saudi Arabia",
    "wishlist_rpc_gross": "194.186",
    "wishlist_rpc_net": "143.938",
    "wishlist_tpc": "1.4"
  },
  {
    "sku_config": "18808ATILJZP",
    "fk_customer": "29567",
    "order_date_key": "10-04-2023",
    "order_nr": "AE1146399863",
    "wishlist_customer": "8544123",
    "wishlist_sku": "18808ATILJZP",
    "wishlist_updated_at": "2023-04-08 11:21:32 UTC",
    "brand": "Wallis",
    "name": "Printed Ruffle Detail Top",
    "activated_at": "2022-05-24 09:40:13 UTC",
    "season": "aw22",
    "color": "Prints",
    "department": "clothing",
    "category": "Tops",
    "subcategory": "Shirts & Blouses",
    "product_gender": "Female",
    "age_group": "Adult",
    "price": "293",
    "price_level": "pl7",
    "merch_type": "General",
    "occasion": "Casual",
    "short_description": "<p><font size=\"3\"><center>This abstract printed Top is a cool update for the new-season wardrobe.</center></p></font><br><li>Lightweight and comfortable polyester fabric</li><li>Ruffle overlays to front</li><li>V-neck with long sleeves</li><li>Secure button down closure to front</li><li>Each item sold separately</li>",
    "namshi_description": "Printed Ruffle Detail Top",
    "special_type": "Discounted",
    "world_tag": "Smart",
    "customer_gender": "female",
    "customer_generation": "1981-1996 Milennials",
    "customer_country_name": "",
    "RPC_gross_per_month": "205.6451515",
    "RPC_net_per_month": "100.1427273",
    "TPC_per_month": "0.545454545",
    "wishlist_customer_gender": "",
    "wishlist_customer_generation": "Not Available",
    "wishlist_customer_country": "United Arab Emirates",
    "wishlist_rpc_gross": "35.15151515",
    "wishlist_rpc_net": "15.88151515",
    "wishlist_tpc": "0.181818182"
  },
  {
    "sku_config": "41064ATYRMIP",
    "fk_customer": "2353369",
    "order_date_key": "10-04-2023",
    "order_nr": "AE1145594815",
    "wishlist_customer": "5949436",
    "wishlist_sku": "41064ATYRMIP",
    "wishlist_updated_at": "2023-04-03 18:18:40 UTC",
    "brand": "Trendyol Curve",
    "name": "Wide Leg Pants",
    "activated_at": "2022-05-18 13:30:16 UTC",
    "season": "aw22",
    "color": "black",
    "department": "clothing",
    "category": "Plus Size Clothing",
    "subcategory": "Pants & Leggings",
    "product_gender": "Female",
    "age_group": "Adult",
    "price": "168",
    "price_level": "pl4",
    "merch_type": "General",
    "occasion": "Casual",
    "short_description": "",
    "namshi_description": "Wide Leg Pants",
    "special_type": "Discounted",
    "world_tag": "",
    "customer_gender": "",
    "customer_generation": "Not Available",
    "customer_country_name": "United Arab Emirates",
    "RPC_gross_per_month": "208.9893506",
    "RPC_net_per_month": "174.0344156",
    "TPC_per_month": "0.311688312",
    "wishlist_customer_gender": "female",
    "wishlist_customer_generation": "Not Available",
    "wishlist_customer_country": "Kuwait",
    "wishlist_rpc_gross": "91.98846154",
    "wishlist_rpc_net": "88.43230769",
    "wishlist_tpc": "0.076923077"
  },
  {
    "sku_config": "12264ATAMQOP",
    "fk_customer": "2495580",
    "order_date_key": "10-04-2023",
    "order_nr": "AE1145958610",
    "wishlist_customer": "999324",
    "wishlist_sku": "12264ATAMQOP",
    "wishlist_updated_at": "2023-04-09 18:00:18 UTC",
    "brand": "Calvin Klein Jeans",
    "name": "Oversized Logo T-Shirt",
    "activated_at": "2022-12-23 11:30:17 UTC",
    "season": "ss23",
    "color": "Black",
    "department": "clothing",
    "category": "T-Shirts & Vests",
    "subcategory": "T-Shirts",
    "product_gender": "Female",
    "age_group": "Adult",
    "price": "303",
    "price_level": "pl8",
    "merch_type": "Premium",
    "occasion": "Casual",
    "short_description": "<p><font size=”3”><center>If you are looking for versatile casual staples; this t-shirt ticks all of the right boxes.</center></p></font><br>Sustainable: Made with transitional cotton; which is produced using sustainable farming practices with the aim of transitioning to organic farming. Grown organically in subtropical countries from non-genetically modified plants; and without the use of any synthetic agricultural chemicals such as fertilizers or pesticides.<br><br><li>Soft and comfortable cotton fabric</li><li>Round neck and short sleeves</li><li>Calvin Klein Jeans signature branding print</li><li>Each item sold separately</li>",
    "namshi_description": "Oversized Logo T-Shirt",
    "special_type": "Discounted",
    "world_tag": "Trend",
    "customer_gender": "female",
    "customer_generation": "1981-1996 Milennials",
    "customer_country_name": "United Arab Emirates",
    "RPC_gross_per_month": "174.2628947",
    "RPC_net_per_month": "140.5032895",
    "TPC_per_month": "0.947368421",
    "wishlist_customer_gender": "female",
    "wishlist_customer_generation": "1997-2012 Generation Z",
    "wishlist_customer_country": "Kuwait",
    "wishlist_rpc_gross": "64.66777778",
    "wishlist_rpc_net": "64.66777778",
    "wishlist_tpc": "0.333333333"
  }
]